[
  {
    "group_name": "Digital art 12",
    "child_name": "Сериков Александр",
    "date": "2023-11-02",
    "report": "\nУ Сериков Александр на текущий момент осталось 0 занятий.\n        ",
    "status": "Отправлен"
  },
  {
    "group_name": "Digital art 12",
    "child_name": "Суслов Матвей Сергеевич",
    "date": "2023-11-02",
    "report": "\nУ Суслов Матвей Сергеевич на текущий момент осталось 0 занятий.\n        ",
    "status": "Отправлен"
  },
  {
    "group_name": "Индив Scratch (Мэргэн)",
    "child_name": "Дарибазарон Мэргэн Булатович",
    "date": "2023-11-02",
    "report": "\nУ Дарибазарон Мэргэн Булатович на текущий момент осталось 0 занятий.\n        ",
    "status": "Не отправлен (Родитель не зарегистрирован в системе)"
  },
  {
    "group_name": "Intermediate 1_2",
    "child_name": "Голяков Максим",
    "date": "2023-11-02",
    "report": "\nУ Голяков Максим на текущий момент осталось 0 занятий.\n        ",
    "status": "Не отправлен (Родитель не зарегистрирован в системе)"
  },
  {
    "group_name": "Intermediate 1_2",
    "child_name": "Кириленко Катерина Сергеевна",
    "date": "2023-11-02",
    "report": "\nУ Кириленко Катерина Сергеевна на текущий момент осталось 0 занятий.\n        ",
    "status": "Отправлен"
  },
  {
    "group_name": "Roblox 1",
    "child_name": "Крылова Ульяна",
    "date": "2023-11-02",
    "report": "\nУ Крылова Ульяна на текущий момент осталось 0 занятий.\n        ",
    "status": "Отправлен"
  },
  {
    "group_name": "Roblox 1",
    "child_name": "Струцкая Соломея",
    "date": "2023-11-02",
    "report": "\nУ Струцкая Соломея на текущий момент осталось 0 занятий.\n        ",
    "status": "Не отправлен (Родитель не зарегистрирован в системе)"
  },
  {
    "group_name": "Индив Python (Леша Король)",
    "child_name": "Король Алексей",
    "date": "2023-11-01",
    "report": "\nУ Король Алексей на текущий момент осталось 0 занятий.\n        ",
    "status": "Отправлен"
  },
  {
    "group_name": "Web (front) 1",
    "child_name": "Малашенко Даниил Романович",
    "date": "2023-11-01",
    "report": "\nУ Малашенко Даниил Романович на текущий момент осталось 0 занятий.\n        ",
    "status": "Не отправлен (Родитель не зарегистрирован в системе)"
  },
  {
    "group_name": "Web (front) 1",
    "child_name": "Малышев Дмитрий Сергеевич",
    "date": "2023-11-01",
    "report": "\nУ Малышев Дмитрий Сергеевич на текущий момент осталось 0 занятий.\n        ",
    "status": "Не отправлен (Родитель не зарегистрирован в системе)"
  },
  {
    "group_name": "Web (front) 2",
    "child_name": "Пашкевич-Григорьев Федор Романович",
    "date": "2023-11-01",
    "report": "\nУ Пашкевич-Григорьев Федор Романович на текущий момент осталось 1 занятий.\n        ",
    "status": "Отправлен"
  },
  {
    "group_name": "Digital art 12",
    "child_name": "Сериков Александр",
    "date": "2023-10-31",
    "report": "\nУ Сериков Александр на текущий момент осталось 0 занятий.\n        ",
    "status": "Отправлен"
  },
  {
    "group_name": "Digital art 12",
    "child_name": "Суслов Матвей Сергеевич",
    "date": "2023-10-31",
    "report": "\nУ Суслов Матвей Сергеевич на текущий момент осталось 0 занятий.\n        ",
    "status": "Отправлен"
  },
  {
    "group_name": "Индив Scratch (Мэргэн)",
    "child_name": "Дарибазарон Мэргэн Булатович",
    "date": "2023-10-31",
    "report": "\nУ Дарибазарон Мэргэн Булатович на текущий момент осталось 0 занятий.\n        ",
    "status": "Не отправлен (Родитель не зарегистрирован в системе)"
  },
  {
    "group_name": "Roblox 1",
    "child_name": "Крылова Ульяна",
    "date": "2023-10-31",
    "report": "\nУ Крылова Ульяна на текущий момент осталось 0 занятий.\n        ",
    "status": "Отправлен"
  },
  {
    "group_name": "Roblox 1",
    "child_name": "Струцкая Соломея",
    "date": "2023-10-31",
    "report": "\nУ Струцкая Соломея на текущий момент осталось 0 занятий.\n        ",
    "status": "Не отправлен (Родитель не зарегистрирован в системе)"
  },
  {
    "group_name": "Digital art 1",
    "child_name": "Иваньковский Мирослав",
    "date": "2023-10-31",
    "report": "\nУ Иваньковский Мирослав на текущий момент осталось 0 занятий.\n        ",
    "status": "Отправлен"
  },
  {
    "group_name": "Индив Python (Леша Король)",
    "child_name": "Король Алексей",
    "date": "2023-10-30",
    "report": "\nУ Король Алексей на текущий момент осталось 0 занятий.\n        ",
    "status": "Отправлен"
  },
  {
    "group_name": "Web (front) 1",
    "child_name": "Малашенко Даниил Романович",
    "date": "2023-10-30",
    "report": "\nУ Малашенко Даниил Романович на текущий момент осталось 0 занятий.\n        ",
    "status": "Не отправлен (Родитель не зарегистрирован в системе)"
  },
  {
    "group_name": "Web (front) 1",
    "child_name": "Малышев Дмитрий Сергеевич",
    "date": "2023-10-30",
    "report": "\nУ Малышев Дмитрий Сергеевич на текущий момент осталось 0 занятий.\n        ",
    "status": "Не отправлен (Родитель не зарегистрирован в системе)"
  },
  {
    "group_name": "Intermediate 1_4",
    "child_name": "Владимир",
    "date": "2023-10-30",
    "report": "\nУ Владимир на текущий момент осталось 0 занятий.\n        ",
    "status": "Не отправлен (Родитель не зарегистрирован в системе)"
  },
  {
    "group_name": "Web (front) 2",
    "child_name": "Пашкевич-Григорьев Федор Романович",
    "date": "2023-10-30",
    "report": "\nУ Пашкевич-Григорьев Федор Романович на текущий момент осталось 1 занятий.\n        ",
    "status": "Отправлен"
  },
  {
    "group_name": "Индив АЯ (Яценко)",
    "child_name": "Яценко Алексей Сергеевич",
    "date": "2023-10-30",
    "report": "\nУ Яценко Алексей Сергеевич на текущий момент осталось 0 занятий.\n        ",
    "status": "Отправлен"
  },
  {
    "group_name": "Intermediate 1_2",
    "child_name": "Голяков Максим",
    "date": "2023-10-30",
    "report": "\nУ Голяков Максим на текущий момент осталось 0 занятий.\n        ",
    "status": "Не отправлен (Родитель не зарегистрирован в системе)"
  },
  {
    "group_name": "Intermediate 1_2",
    "child_name": "Кириленко Катерина Сергеевна",
    "date": "2023-10-30",
    "report": "\nУ Кириленко Катерина Сергеевна на текущий момент осталось 0 занятий.\n        ",
    "status": "Отправлен"
  },
  {
    "group_name": "Python_1",
    "child_name": "Платон Прохорчук",
    "date": "2023-10-28",
    "report": "\nУ Платон Прохорчук на текущий момент осталось 0 занятий.\n        ",
    "status": "Отправлен"
  },
  {
    "group_name": "Python_1",
    "child_name": "Платон Прохорчук",
    "date": "2023-10-28",
    "report": "\nУ Платон Прохорчук на текущий момент осталось 0 занятий.\n        ",
    "status": "Отправлен"
  },
  {
    "group_name": "Unity_3",
    "child_name": "Васильев Клим",
    "date": "2023-10-28",
    "report": "\nУ Васильев Клим на текущий момент осталось 0 занятий.\n        ",
    "status": "Отправлен"
  },
  {
    "group_name": "Unity_3",
    "child_name": "Ермаков Даниил Николаевич",
    "date": "2023-10-28",
    "report": "\nУ Ермаков Даниил Николаевич на текущий момент осталось 1 занятий.\n        ",
    "status": "Отправлен"
  },
  {
    "group_name": "Unity_3",
    "child_name": "Васильев Клим",
    "date": "2023-10-28",
    "report": "\nУ Васильев Клим на текущий момент осталось 0 занятий.\n        ",
    "status": "Отправлен"
  },
  {
    "group_name": "Unity_3",
    "child_name": "Ермаков Даниил Николаевич",
    "date": "2023-10-28",
    "report": "\nУ Ермаков Даниил Николаевич на текущий момент осталось 1 занятий.\n        ",
    "status": "Отправлен"
  },
  {
    "group_name": "Intermediate 1_4",
    "child_name": "Владимир",
    "date": "2023-10-28",
    "report": "\nУ Владимир на текущий момент осталось 0 занятий.\n        ",
    "status": "Не отправлен (Родитель не зарегистрирован в системе)"
  },
  {
    "group_name": "Индив АЯ (Яценко)",
    "child_name": "Яценко Алексей Сергеевич",
    "date": "2023-10-28",
    "report": "\nУ Яценко Алексей Сергеевич на текущий момент осталось 0 занятий.\n        ",
    "status": "Отправлен"
  },
  {
    "group_name": "Digital art 1",
    "child_name": "Иваньковский Мирослав",
    "date": "2023-10-27",
    "report": "\nУ Иваньковский Мирослав на текущий момент осталось 0 занятий.\n        ",
    "status": "Отправлен"
  },
  {
    "group_name": "Digital art 12",
    "child_name": "Сериков Александр",
    "date": "2023-10-26",
    "report": "\nУ Сериков Александр на текущий момент осталось 0 занятий.\n        ",
    "status": "Отправлен"
  },
  {
    "group_name": "Digital art 12",
    "child_name": "Суслов Матвей Сергеевич",
    "date": "2023-10-26",
    "report": "\nУ Суслов Матвей Сергеевич на текущий момент осталось 0 занятий.\n        ",
    "status": "Отправлен"
  },
  {
    "group_name": "Индив Scratch (Мэргэн)",
    "child_name": "Дарибазарон Мэргэн Булатович",
    "date": "2023-10-26",
    "report": "\nУ Дарибазарон Мэргэн Булатович на текущий момент осталось 0 занятий.\n        ",
    "status": "Не отправлен (Родитель не зарегистрирован в системе)"
  },
  {
    "group_name": "Intermediate 1_2",
    "child_name": "Голяков Максим",
    "date": "2023-10-26",
    "report": "\nУ Голяков Максим на текущий момент осталось 0 занятий.\n        ",
    "status": "Не отправлен (Родитель не зарегистрирован в системе)"
  },
  {
    "group_name": "Intermediate 1_2",
    "child_name": "Кириленко Катерина Сергеевна",
    "date": "2023-10-26",
    "report": "\nУ Кириленко Катерина Сергеевна на текущий момент осталось 0 занятий.\n        ",
    "status": "Отправлен"
  },
  {
    "group_name": "Roblox 1",
    "child_name": "Крылова Ульяна",
    "date": "2023-10-26",
    "report": "\nУ Крылова Ульяна на текущий момент осталось 0 занятий.\n        ",
    "status": "Отправлен"
  },
  {
    "group_name": "Roblox 1",
    "child_name": "Струцкая Соломея",
    "date": "2023-10-26",
    "report": "\nУ Струцкая Соломея на текущий момент осталось 0 занятий.\n        ",
    "status": "Не отправлен (Родитель не зарегистрирован в системе)"
  },
  {
    "group_name": "Unity_1",
    "child_name": "Ишин Дмитрий",
    "date": "2023-10-26",
    "report": "\nУ Ишин Дмитрий на текущий момент осталось 0 занятий.\n        ",
    "status": "Отправлен"
  },
  {
    "group_name": "Web (front) 1",
    "child_name": "Малашенко Даниил Романович",
    "date": "2023-10-25",
    "report": "\nУ Малашенко Даниил Романович на текущий момент осталось 0 занятий.\n        ",
    "status": "Не отправлен (Родитель не зарегистрирован в системе)"
  },
  {
    "group_name": "Web (front) 1",
    "child_name": "Малышев Дмитрий Сергеевич",
    "date": "2023-10-25",
    "report": "\nУ Малышев Дмитрий Сергеевич на текущий момент осталось 0 занятий.\n        ",
    "status": "Не отправлен (Родитель не зарегистрирован в системе)"
  },
  {
    "group_name": "Web (front) 2",
    "child_name": "Пашкевич-Григорьев Федор Романович",
    "date": "2023-10-25",
    "report": "\nУ Пашкевич-Григорьев Федор Романович на текущий момент осталось 1 занятий.\n        ",
    "status": "Отправлен"
  },
  {
    "group_name": "Digital art 12",
    "child_name": "Сериков Александр",
    "date": "2023-10-24",
    "report": "\nУ Сериков Александр на текущий момент осталось 0 занятий.\n        ",
    "status": "Отправлен"
  },
  {
    "group_name": "Digital art 12",
    "child_name": "Суслов Матвей Сергеевич",
    "date": "2023-10-24",
    "report": "\nУ Суслов Матвей Сергеевич на текущий момент осталось 0 занятий.\n        ",
    "status": "Отправлен"
  },
  {
    "group_name": "Индив Scratch (Мэргэн)",
    "child_name": "Дарибазарон Мэргэн Булатович",
    "date": "2023-10-24",
    "report": "\nУ Дарибазарон Мэргэн Булатович на текущий момент осталось 0 занятий.\n        ",
    "status": "Не отправлен (Родитель не зарегистрирован в системе)"
  },
  {
    "group_name": "Roblox 1",
    "child_name": "Крылова Ульяна",
    "date": "2023-10-24",
    "report": "\nУ Крылова Ульяна на текущий момент осталось 0 занятий.\n        ",
    "status": "Отправлен"
  },
  {
    "group_name": "Roblox 1",
    "child_name": "Струцкая Соломея",
    "date": "2023-10-24",
    "report": "\nУ Струцкая Соломея на текущий момент осталось 0 занятий.\n        ",
    "status": "Не отправлен (Родитель не зарегистрирован в системе)"
  },
  {
    "group_name": "Unity_1",
    "child_name": "Ишин Дмитрий",
    "date": "2023-10-24",
    "report": "\nУ Ишин Дмитрий на текущий момент осталось 0 занятий.\n        ",
    "status": "Отправлен"
  },
  {
    "group_name": "Digital art 1",
    "child_name": "Иваньковский Мирослав",
    "date": "2023-10-24",
    "report": "\nУ Иваньковский Мирослав на текущий момент осталось 0 занятий.\n        ",
    "status": "Отправлен"
  },
  {
    "group_name": "Web (front) 1",
    "child_name": "Малашенко Даниил Романович",
    "date": "2023-10-23",
    "report": "\nУ Малашенко Даниил Романович на текущий момент осталось 0 занятий.\n        ",
    "status": "Не отправлен (Родитель не зарегистрирован в системе)"
  },
  {
    "group_name": "Web (front) 1",
    "child_name": "Малышев Дмитрий Сергеевич",
    "date": "2023-10-23",
    "report": "\nУ Малышев Дмитрий Сергеевич на текущий момент осталось 0 занятий.\n        ",
    "status": "Не отправлен (Родитель не зарегистрирован в системе)"
  },
  {
    "group_name": "Intermediate 1_4",
    "child_name": "Владимир",
    "date": "2023-10-23",
    "report": "\nУ Владимир на текущий момент осталось 0 занятий.\n        ",
    "status": "Не отправлен (Родитель не зарегистрирован в системе)"
  },
  {
    "group_name": "Индив АЯ (Яценко)",
    "child_name": "Яценко Алексей Сергеевич",
    "date": "2023-10-23",
    "report": "\nУ Яценко Алексей Сергеевич на текущий момент осталось 0 занятий.\n        ",
    "status": "Отправлен"
  },
  {
    "group_name": "Intermediate 1_2",
    "child_name": "Голяков Максим",
    "date": "2023-10-23",
    "report": "\nУ Голяков Максим на текущий момент осталось 0 занятий.\n        ",
    "status": "Не отправлен (Родитель не зарегистрирован в системе)"
  },
  {
    "group_name": "Intermediate 1_2",
    "child_name": "Кириленко Катерина Сергеевна",
    "date": "2023-10-23",
    "report": "\nУ Кириленко Катерина Сергеевна на текущий момент осталось 0 занятий.\n        ",
    "status": "Отправлен"
  },
  {
    "group_name": "Python_1",
    "child_name": "Король Алексей",
    "date": "2023-10-23",
    "report": "\nУ Король Алексей на текущий момент осталось 0 занятий.\n        ",
    "status": "Отправлен"
  },
  {
    "group_name": "Python_1",
    "child_name": "Платон Прохорчук",
    "date": "2023-10-23",
    "report": "\nУ Платон Прохорчук на текущий момент осталось 0 занятий.\n        ",
    "status": "Отправлен"
  },
  {
    "group_name": "Индив Scratch (Мэргэн)",
    "child_name": "Дарибазарон Мэргэн Булатович",
    "date": "2023-10-22",
    "report": "\nУ Дарибазарон Мэргэн Булатович на текущий момент осталось 0 занятий.\n        ",
    "status": "Не отправлен (Родитель не зарегистрирован в системе)"
  },
  {
    "group_name": "Unity_3",
    "child_name": "Васильев Клим",
    "date": "2023-10-21",
    "report": "\nУ Васильев Клим на текущий момент осталось 0 занятий.\n        ",
    "status": "Отправлен"
  },
  {
    "group_name": "Unity_3",
    "child_name": "Ермаков Даниил Николаевич",
    "date": "2023-10-21",
    "report": "\nУ Ермаков Даниил Николаевич на текущий момент осталось 1 занятий.\n        ",
    "status": "Отправлен"
  },
  {
    "group_name": "Unity_3",
    "child_name": "Васильев Клим",
    "date": "2023-10-21",
    "report": "\nУ Васильев Клим на текущий момент осталось 0 занятий.\n        ",
    "status": "Отправлен"
  },
  {
    "group_name": "Unity_3",
    "child_name": "Ермаков Даниил Николаевич",
    "date": "2023-10-21",
    "report": "\nУ Ермаков Даниил Николаевич на текущий момент осталось 1 занятий.\n        ",
    "status": "Отправлен"
  },
  {
    "group_name": "Intermediate 1_4",
    "child_name": "Владимир",
    "date": "2023-10-21",
    "report": "\nУ Владимир на текущий момент осталось 0 занятий.\n        ",
    "status": "Не отправлен (Родитель не зарегистрирован в системе)"
  },
  {
    "group_name": "Digital art 1",
    "child_name": "Ганеев Тимур",
    "date": "2023-10-20",
    "report": "\nУ Ганеев Тимур на текущий момент осталось 0 занятий.\n        ",
    "status": "Не отправлен (Родитель не зарегистрирован в системе)"
  },
  {
    "group_name": "Digital art 1",
    "child_name": "Иваньковский Мирослав",
    "date": "2023-10-20",
    "report": "\nУ Иваньковский Мирослав на текущий момент осталось 0 занятий.\n        ",
    "status": "Отправлен"
  },
  {
    "group_name": "Intermediate 1_2",
    "child_name": "Голяков Максим",
    "date": "2023-10-19",
    "report": "\nУ Голяков Максим на текущий момент осталось 0 занятий.\n        ",
    "status": "Не отправлен (Родитель не зарегистрирован в системе)"
  },
  {
    "group_name": "Intermediate 1_2",
    "child_name": "Кириленко Катерина Сергеевна",
    "date": "2023-10-19",
    "report": "\nУ Кириленко Катерина Сергеевна на текущий момент осталось 0 занятий.\n        ",
    "status": "Отправлен"
  },
  {
    "group_name": "Roblox 1",
    "child_name": "Крылова Ульяна",
    "date": "2023-10-19",
    "report": "\nУ Крылова Ульяна на текущий момент осталось 0 занятий.\n        ",
    "status": "Отправлен"
  },
  {
    "group_name": "Roblox 1",
    "child_name": "Струцкая Соломея",
    "date": "2023-10-19",
    "report": "\nУ Струцкая Соломея на текущий момент осталось 0 занятий.\n        ",
    "status": "Не отправлен (Родитель не зарегистрирован в системе)"
  },
  {
    "group_name": "Unity_1",
    "child_name": "Ишин Дмитрий",
    "date": "2023-10-19",
    "report": "\nУ Ишин Дмитрий на текущий момент осталось 0 занятий.\n        ",
    "status": "Отправлен"
  },
  {
    "group_name": "Digital art 12",
    "child_name": "Сериков Александр",
    "date": "2023-10-19",
    "report": "\nУ Сериков Александр на текущий момент осталось 0 занятий.\n        ",
    "status": "Отправлен"
  },
  {
    "group_name": "Digital art 12",
    "child_name": "Суслов Матвей Сергеевич",
    "date": "2023-10-19",
    "report": "\nУ Суслов Матвей Сергеевич на текущий момент осталось 0 занятий.\n        ",
    "status": "Отправлен"
  },
  {
    "group_name": "Web (front) 1",
    "child_name": "Малашенко Даниил Романович",
    "date": "2023-10-18",
    "report": "\nУ Малашенко Даниил Романович на текущий момент осталось 0 занятий.\n        ",
    "status": "Не отправлен (Родитель не зарегистрирован в системе)"
  },
  {
    "group_name": "Web (front) 1",
    "child_name": "Малышев Дмитрий Сергеевич",
    "date": "2023-10-18",
    "report": "\nУ Малышев Дмитрий Сергеевич на текущий момент осталось 0 занятий.\n        ",
    "status": "Не отправлен (Родитель не зарегистрирован в системе)"
  },
  {
    "group_name": "Web (front) 2",
    "child_name": "Пашкевич-Григорьев Федор Романович",
    "date": "2023-10-18",
    "report": "\nУ Пашкевич-Григорьев Федор Романович на текущий момент осталось 1 занятий.\n        ",
    "status": "Отправлен"
  },
  {
    "group_name": "Индив АЯ (Яценко)",
    "child_name": "Яценко Алексей Сергеевич",
    "date": "2023-10-18",
    "report": "\nУ Яценко Алексей Сергеевич на текущий момент осталось 0 занятий.\n        ",
    "status": "Отправлен"
  },
  {
    "group_name": "Elementary 2_2",
    "child_name": "Васенина Варвара",
    "date": "2023-10-18",
    "report": "\nУ Васенина Варвара на текущий момент осталось 0 занятий.\n        ",
    "status": "Не отправлен (Родитель не зарегистрирован в системе)"
  },
  {
    "group_name": "Python_1",
    "child_name": "Король Алексей",
    "date": "2023-10-18",
    "report": "\nУ Король Алексей на текущий момент осталось 0 занятий.\n        ",
    "status": "Отправлен"
  },
  {
    "group_name": "Python_1",
    "child_name": "Платон Прохорчук",
    "date": "2023-10-18",
    "report": "\nУ Платон Прохорчук на текущий момент осталось 0 занятий.\n        ",
    "status": "Отправлен"
  },
  {
    "group_name": "Индив Scratch (Мэргэн)",
    "child_name": "Дарибазарон Мэргэн Булатович",
    "date": "2023-10-17",
    "report": "\nУ Дарибазарон Мэргэн Булатович на текущий момент осталось 0 занятий.\n        ",
    "status": "Не отправлен (Родитель не зарегистрирован в системе)"
  },
  {
    "group_name": "Roblox 1",
    "child_name": "Крылова Ульяна",
    "date": "2023-10-17",
    "report": "\nУ Крылова Ульяна на текущий момент осталось 0 занятий.\n        ",
    "status": "Отправлен"
  },
  {
    "group_name": "Roblox 1",
    "child_name": "Струцкая Соломея",
    "date": "2023-10-17",
    "report": "\nУ Струцкая Соломея на текущий момент осталось 0 занятий.\n        ",
    "status": "Не отправлен (Родитель не зарегистрирован в системе)"
  },
  {
    "group_name": "Unity_1",
    "child_name": "Ишин Дмитрий",
    "date": "2023-10-17",
    "report": "\nУ Ишин Дмитрий на текущий момент осталось 0 занятий.\n        ",
    "status": "Отправлен"
  },
  {
    "group_name": "Digital art 1",
    "child_name": "Ганеев Тимур",
    "date": "2023-10-17",
    "report": "\nУ Ганеев Тимур на текущий момент осталось 0 занятий.\n        ",
    "status": "Не отправлен (Родитель не зарегистрирован в системе)"
  },
  {
    "group_name": "Digital art 1",
    "child_name": "Иваньковский Мирослав",
    "date": "2023-10-17",
    "report": "\nУ Иваньковский Мирослав на текущий момент осталось 0 занятий.\n        ",
    "status": "Отправлен"
  },
  {
    "group_name": "Web (front) 1",
    "child_name": "Малашенко Даниил Романович",
    "date": "2023-10-16",
    "report": "\nУ Малашенко Даниил Романович на текущий момент осталось 0 занятий.\n        ",
    "status": "Не отправлен (Родитель не зарегистрирован в системе)"
  },
  {
    "group_name": "Web (front) 1",
    "child_name": "Малышев Дмитрий Сергеевич",
    "date": "2023-10-16",
    "report": "\nУ Малышев Дмитрий Сергеевич на текущий момент осталось 0 занятий.\n        ",
    "status": "Не отправлен (Родитель не зарегистрирован в системе)"
  },
  {
    "group_name": "Intermediate 1_4",
    "child_name": "Владимир",
    "date": "2023-10-16",
    "report": "\nУ Владимир на текущий момент осталось 0 занятий.\n        ",
    "status": "Не отправлен (Родитель не зарегистрирован в системе)"
  },
  {
    "group_name": "Web (front) 2",
    "child_name": "Пашкевич-Григорьев Федор Романович",
    "date": "2023-10-16",
    "report": "\nУ Пашкевич-Григорьев Федор Романович на текущий момент осталось 1 занятий.\n        ",
    "status": "Отправлен"
  },
  {
    "group_name": "Индив АЯ (Яценко)",
    "child_name": "Яценко Алексей Сергеевич",
    "date": "2023-10-16",
    "report": "\nУ Яценко Алексей Сергеевич на текущий момент осталось 0 занятий.\n        ",
    "status": "Отправлен"
  },
  {
    "group_name": "Intermediate 1_2",
    "child_name": "Голяков Максим",
    "date": "2023-10-16",
    "report": "\nУ Голяков Максим на текущий момент осталось 0 занятий.\n        ",
    "status": "Не отправлен (Родитель не зарегистрирован в системе)"
  },
  {
    "group_name": "Intermediate 1_2",
    "child_name": "Кириленко Катерина Сергеевна",
    "date": "2023-10-16",
    "report": "\nУ Кириленко Катерина Сергеевна на текущий момент осталось 0 занятий.\n        ",
    "status": "Отправлен"
  },
  {
    "group_name": "Elementary 2_2",
    "child_name": "Васенина Варвара",
    "date": "2023-10-16",
    "report": "\nУ Васенина Варвара на текущий момент осталось 0 занятий.\n        ",
    "status": "Не отправлен (Родитель не зарегистрирован в системе)"
  },
  {
    "group_name": "Python_1",
    "child_name": "Король Алексей",
    "date": "2023-10-16",
    "report": "\nУ Король Алексей на текущий момент осталось 0 занятий.\n        ",
    "status": "Отправлен"
  },
  {
    "group_name": "Python_1",
    "child_name": "Платон Прохорчук",
    "date": "2023-10-16",
    "report": "\nУ Платон Прохорчук на текущий момент осталось 0 занятий.\n        ",
    "status": "Отправлен"
  }
]